odoo/addons/stock_location_tray/README.rst
odoo/addons/stock_location_tray/__init__.py
odoo/addons/stock_location_tray/__manifest__.py
odoo/addons/stock_location_tray/demo/stock_location_demo.xml
odoo/addons/stock_location_tray/demo/stock_location_tray_type_demo.xml
odoo/addons/stock_location_tray/i18n/stock_location_tray.pot
odoo/addons/stock_location_tray/models/__init__.py
odoo/addons/stock_location_tray/models/stock_location.py
odoo/addons/stock_location_tray/models/stock_location_tray_type.py
odoo/addons/stock_location_tray/models/stock_move_line.py
odoo/addons/stock_location_tray/readme/CONFIGURE.rst
odoo/addons/stock_location_tray/readme/CONTRIBUTORS.rst
odoo/addons/stock_location_tray/readme/CREDITS.rst
odoo/addons/stock_location_tray/readme/DESCRIPTION.rst
odoo/addons/stock_location_tray/readme/ROADMAP.rst
odoo/addons/stock_location_tray/security/ir.model.access.csv
odoo/addons/stock_location_tray/static/description/icon.png
odoo/addons/stock_location_tray/static/description/index.html
odoo/addons/stock_location_tray/static/description/location-tray.png
odoo/addons/stock_location_tray/static/src/js/stock_location_tray.js
odoo/addons/stock_location_tray/static/src/scss/stock_location_tray.scss
odoo/addons/stock_location_tray/tests/__init__.py
odoo/addons/stock_location_tray/tests/common.py
odoo/addons/stock_location_tray/tests/test_location.py
odoo/addons/stock_location_tray/tests/test_stock_move_line.py
odoo/addons/stock_location_tray/tests/test_tray_type.py
odoo/addons/stock_location_tray/views/stock_location_tray_templates.xml
odoo/addons/stock_location_tray/views/stock_location_tray_type_views.xml
odoo/addons/stock_location_tray/views/stock_location_views.xml
odoo/addons/stock_location_tray/views/stock_move_line_views.xml
odoo14_addon_stock_location_tray-14.0.1.1.3.dist-info/METADATA
odoo14_addon_stock_location_tray-14.0.1.1.3.dist-info/WHEEL
odoo14_addon_stock_location_tray-14.0.1.1.3.dist-info/top_level.txt
odoo14_addon_stock_location_tray-14.0.1.1.3.dist-info/RECORD
